uart/header/parameter.vh
`ifndef parameter_vh
`define parameter_vh

`define unit_1ns 1_000_000_000

`define clk100MHz 100_000_000
`define clk200MHz 200_000_000
`define clk300MHz 300_000_000
`define clk400MHz 400_000_000
`define clk500MHz 500_000_000
`define clk1GHz  1000_000_000

`define bitwidth5 5
`define bitwidth6 6
`define bitwidth7 7
`define bitwidth8 8

`define baud9600    9_600
`define baud19200   19_200
`define baud38400   38_400
`define baud57600   57_600
`define baud115200  115_200
`define baud230400  230_400
`define baud460800  460_800
`define baud921600  921_600

`define baud_slow   9600
`define baud_mid    115200
`define baud_fast   921600

`endif

uart/rtl/receive.v
`timescale 1ns/1ps

module receive#(
	parameter bits =8,
	parameter oversample =16)(
	clk, en, in, rst,
	out, done, busy, error);
	localparam bitsWidth =$clog2(bits);
	localparam osrWidth  =$clog2(oversample);
	localparam osrHalf   =oversample/2;

	localparam reset     =3'd0;
	localparam idle      =3'd1;
	localparam startBit  =3'd2;
	localparam dataBits  =3'd3;
	localparam stopBit   =3'd4;

	localparam [(bitsWidth-1):0] last =(bits-1);

	input wire clk, en, in, rst;
	output reg [(bits-1):0] out;
	output reg done, busy, error;

	reg [2:0]             state       =reset;
	reg [(bits-1):0]      data        =1'd0;
	reg [(bitsWidth-1):0] bitIndex    =1'd0;
	reg [(osrWidth-1):0]  sampleCount =1'd0;

	//Two registers for mitigating Metastability
	reg inFF0 =1'b1, inFF1 =1'b1;
	wire rx =inFF1;

	always@(posedge clk)begin
		
		inFF0 <= in;
		inFF1 <= inFF0;

		if (rst)begin
			state <=idle;
			out   <=1'd0;
			done  <=1'b0;
			busy  <=1'b0;
			error <=1'b0;
			data  <=1'd0;
			sampleCount <=1'd0;
			bitIndex <=1'd0;
		end
		else begin
			case(state)
				/*
				reset:begin
					out   <='0;
					done  <=1'b0;
					busy  <=1'b0;
					error <=1'b0;
					data  <='0;
					state <=idle;
				end
				*/
				idle:begin
					busy     <=1'b0;
					bitIndex <=1'd0;
					data     <=1'd0;
					error    <=1'b0;
					done     <=1'b0;
					sampleCount <=1'd0;
					if(en&(~rx))begin
						busy <=1'b1;
						state <=startBit;
					end
				end
				startBit:begin
					if(sampleCount==(osrHalf-1))begin
						sampleCount <=1'd0;
						if(~rx)begin
							bitIndex <=1'd0;
							state    <=dataBits;
						end
						else begin
							busy  <=1'b0;
							state <=idle;
						end
					end
					else sampleCount <=(sampleCount+1'b1);
				end
				dataBits:begin
					if(sampleCount==(oversample-1))begin
						sampleCount <=1'd0;
						data[bitIndex] <=rx;
						if(bitIndex==last)begin
							state <=stopBit;
						end
						else bitIndex <=(bitIndex+1'b1);
					end
					else sampleCount <=(sampleCount+1'b1);
				end
				stopBit:begin
					if(sampleCount==(oversample-1))begin
						sampleCount <=1'd0;
						if(!rx) error <=1'b1;
						out <=data;
						done <=1'b1;
						busy <=1'b0;
						state<=idle;
					end
					else sampleCount <=(sampleCount+1'b1);
				end
				default: state <=idle;
			endcase
		end
	end
endmodule

uart/rtl/transmit.v
`timescale 1ns/1ps

module transmit #(
	parameter bits =8)(
	clk, en, start,
	in,
	out, done, busy);
	localparam bitsWidth =$clog2(bits);
	localparam reset     =3'd0;
	localparam idle      =3'd1;
	localparam startBit  =3'd2;
	localparam dataBits  =3'd3;
	localparam stopBit   =3'd4;

	input wire clk, en, start;
	input wire [(bits-1):0] in;
	output reg out, done, busy;

	reg [3:0] state =reset;
	reg [(bits-1):0] data =0;

	reg [(bitsWidth-1):0] bitIndex =0;

	always@(posedge clk)begin
		case(state)
			reset:begin
				out <=1'b1;
				done <=1'b0;
				busy <=1'b0;
				data <='0;
				bitIndex <='0;
				state <= idle;
			end
			idle:begin 
				//if out becomes 0, Transmission starts
				out <=1'b1;
				done <=1'b0;
				bitIndex <=1'd0;
				data <=1'd0;
				if(start&en) state <=startBit;
			end
			startBit:begin
				data <=in;
				out <=1'b0;
				busy <=1'b1;
				state <=dataBits;
			end
			dataBits:begin
				out <=data[bitIndex];
				//if(&bitIndex)begin
				if(bitIndex==(bits-1))begin
					bitIndex <=0;
					state <=stopBit;
				end
				else bitIndex <=(bitIndex+1'b1);
			end
			stopBit:begin
				done <=1'b1;
				data <='b0;
				out <=1'b1;
				busy <=1'b0;
				state <=idle;
			end
			default: state <=reset;
		endcase
	end
endmodule

uart/rtl/baudrategen.v
`timescale 1ns/1ps

module baudrategen#(
	parameter clock =100_000_000,
	parameter baudrate =115_200,
	parameter oversample =16)(
	input wire clk,
	output reg RXclk, output reg TXclk
	);
	localparam maxRateRX =clock/(2*baudrate*oversample);
	localparam maxRateTX =clock/(2*baudrate);
	localparam RXcountWidth =$clog2(maxRateRX+1);
	localparam TXcountWidth =$clog2(maxRateTX+1);

	reg [(RXcountWidth-1):0] RXcount=0;
	reg [(TXcountWidth-1):0] TXcount=0;

	initial begin
		RXclk =1'b0;
		TXclk =1'b0;
	end

	always@(posedge clk)begin
		if(RXcount==(maxRateRX))begin
			RXcount <=0;
			RXclk <=~RXclk;
		end
		else RXcount <=(RXcount +1'b1);
		if(TXcount==(maxRateTX))begin
			TXcount <=0;
			TXclk <=~TXclk;
		end
		else TXcount <=(TXcount+1'b1);
	end
endmodule

uart/testbench/receive/tb_receive.v
`include "parameter.vh"
`include "transmit.v"
`include "baudrategen.v"
`include "receive.v"
`timescale 1ns/1ps

module tb_transmitter;
	parameter integer clock =`clk500MHz;
	parameter integer latency = (1_000_000_000/(2*clock));
	parameter integer baudrate =`baud_fast;
	parameter integer bitwidth =`bitwidth8;
	parameter integer oversample =16;

	localparam integer clockTick =(clock/baudrate)*2*latency;

	reg clk =1'b0;
	wire RXclk, TXclk;
	
	reg TXen =1'b1;
	reg TXstart =0;
	reg [(bitwidth-1):0] in ='0;

	wire TXout;
	wire TXdone;
	wire TXbusy;
	
	reg RXen =1'b1;
	reg RXrst =1'b0;
	wire [(bitwidth-1):0] RXout;
	wire RXdone, RXbusy, RXerror;
	

	baudrategen #(clock,baudrate,16) baudgen(clk, RXclk, TXclk);

	transmit #(bitwidth) transmit0(TXclk, TXen, TXstart, in, TXout, TXdone, TXbusy);
	receive  #(bitwidth) receive0(RXclk, RXen, TXout, RXrst, RXout, RXdone, RXbusy, RXerror);

	task test;
		input [(bitwidth-1):0] in_t;
		in <= in_t;
		#clockTick TXstart <=1'b1;
		#clockTick TXstart <=1'b0;
		#clockTick;
		#(bitwidth*clockTick);
		#clockTick;
		#clockTick;
	endtask
	
	initial begin
		$dumpfile("out.vcd");
		$dumpvars(0,tb_transmitter);
		test(8'h55);
		test(8'h96);
		test(8'h47);
		test(8'h0c);
		$finish;
	end
	always #latency clk =~clk;
endmodule

uart/testbench/receive/out.vcd
$date
	Wed Feb  4 22:23:59 2026
$end
$version
	Icarus Verilog
$end
$timescale
	1ps
$end
$scope module tb_transmitter $end
$var wire 1 ! TXout $end
$var wire 1 " TXdone $end
$var wire 1 # TXclk $end
$var wire 1 $ TXbusy $end
$var wire 8 % RXout [7:0] $end
$var wire 1 & RXerror $end
$var wire 1 ' RXdone $end
$var wire 1 ( RXclk $end
$var wire 1 ) RXbusy $end
$var parameter 32 * baudrate $end
$var parameter 32 + bitwidth $end
$var parameter 32 , clock $end
$var parameter 32 - clockTick $end
$var parameter 32 . latency $end
$var parameter 32 / oversample $end
$var reg 1 0 RXen $end
$var reg 1 1 RXrst $end
$var reg 1 2 TXen $end
$var reg 1 3 TXstart $end
$var reg 1 4 clk $end
$var reg 8 5 in [7:0] $end
$scope module baudgen $end
$var wire 1 4 clk $end
$var parameter 32 6 RXcountWidth $end
$var parameter 32 7 TXcountWidth $end
$var parameter 32 8 baudrate $end
$var parameter 32 9 clock $end
$var parameter 96 : maxRateRX $end
$var parameter 64 ; maxRateTX $end
$var parameter 32 < oversample $end
$var reg 1 ( RXclk $end
$var reg 5 = RXcount [4:0] $end
$var reg 1 # TXclk $end
$var reg 9 > TXcount [8:0] $end
$upscope $end
$scope module receive0 $end
$var wire 1 ( clk $end
$var wire 1 0 en $end
$var wire 1 1 rst $end
$var wire 1 ? rx $end
$var wire 1 ! in $end
$var parameter 32 @ bits $end
$var parameter 32 A bitsWidth $end
$var parameter 3 B dataBits $end
$var parameter 3 C idle $end
$var parameter 3 D last $end
$var parameter 32 E osrHalf $end
$var parameter 32 F osrWidth $end
$var parameter 32 G oversample $end
$var parameter 3 H reset $end
$var parameter 3 I startBit $end
$var parameter 3 J stopBit $end
$var reg 3 K bitIndex [2:0] $end
$var reg 1 ) busy $end
$var reg 8 L data [7:0] $end
$var reg 1 ' done $end
$var reg 1 & error $end
$var reg 1 M inFF0 $end
$var reg 1 N inFF1 $end
$var reg 8 O out [7:0] $end
$var reg 4 P sampleCount [3:0] $end
$var reg 3 Q state [2:0] $end
$upscope $end
$scope module transmit0 $end
$var wire 1 # clk $end
$var wire 1 2 en $end
$var wire 8 R in [7:0] $end
$var wire 1 3 start $end
$var parameter 32 S bits $end
$var parameter 32 T bitsWidth $end
$var parameter 3 U dataBits $end
$var parameter 3 V idle $end
$var parameter 3 W reset $end
$var parameter 3 X startBit $end
$var parameter 3 Y stopBit $end
$var reg 3 Z bitIndex [2:0] $end
$var reg 1 $ busy $end
$var reg 8 [ data [7:0] $end
$var reg 1 " done $end
$var reg 1 ! out $end
$var reg 4 \ state [3:0] $end
$upscope $end
$scope task test $end
$var reg 8 ] in_t [7:0] $end
$upscope $end
$upscope $end
$enddefinitions $end
$comment Show the parameter values. $end
$dumpall
b100 Y
b10 X
b0 W
b1 V
b11 U
b11 T
b1000 S
b100 J
b10 I
b0 H
b10000 G
b100 F
b1000 E
b111 D
b1 C
b11 B
b11 A
b1000 @
b10000 <
b100001111 ;
b10000 :
b11101110011010110010100000000 9
b11100001000000000000 8
b1001 7
b101 6
b10000 /
b1 .
b10000111100 -
b11101110011010110010100000000 ,
b1000 +
b11100001000000000000 *
$end
#0
$dumpvars
b1010101 ]
b0 \
b0 [
b0 Z
b1010101 R
b0 Q
b0 P
bx O
1N
1M
b0 L
b0 K
1?
b0 >
b0 =
b1010101 5
04
03
12
01
10
x)
0(
x'
x&
bx %
x$
0#
x"
x!
$end
#1000
b1 >
b1 =
14
#2000
04
#3000
b10 >
b10 =
14
#4000
04
#5000
b11 >
b11 =
14
#6000
04
#7000
b100 >
b100 =
14
#8000
04
#9000
b101 >
b101 =
14
#10000
04
#11000
b110 >
b110 =
14
#12000
04
#13000
b111 >
b111 =
14
#14000
04
#15000
b1000 >
b1000 =
14
#16000
04
#17000
b1001 >
b1001 =
14
#18000
04
#19000
b1010 >
b1010 =
14
#20000
04
#21000
b1011 >
b1011 =
14
#22000
04
#23000
b1100 >
b1100 =
14
#24000
04
#25000
b1101 >
b1101 =
14
#26000
04
#27000
b1110 >
b1110 =
14
#28000
04
#29000
b1111 >
b1111 =
14
#30000
04
#31000
b10000 >
b10000 =
14
#32000
04
#33000
b1 Q
xM
b10001 >
1(
b0 =
14
#34000
04
#35000
b10010 >
b1 =
14
#36000
04
#37000
b10011 >
b10 =
14
#38000
04
#39000
b10100 >
b11 =
14
#40000
04
#41000
b10101 >
b100 =
14
#42000
04
#43000
b10110 >
b101 =
14
#44000
04
#45000
b10111 >
b110 =
14
#46000
04
#47000
b11000 >
b111 =
14
#48000
04
#49000
b11001 >
b1000 =
14
#50000
04
#51000
b11010 >
b1001 =
14
#52000
04
#53000
b11011 >
b1010 =
14
#54000
04
#55000
b11100 >
b1011 =
14
#56000
04
#57000
b11101 >
b1100 =
14
#58000
04
#59000
b11110 >
b1101 =
14
#60000
04
#61000
b11111 >
b1110 =
14
#62000
04
#63000
b100000 >
b1111 =
14
#64000
04
#65000
b100001 >
b10000 =
14
#66000
04
#67000
b100010 >
0(
b0 =
14
#68000
04
#69000
b100011 >
b1 =
14
#70000
04
#71000
b100100 >
b10 =
14
#72000
04
#73000
b100101 >
b11 =
14
#74000
04
#75000
b100110 >
b100 =
14
#76000
04
#77000
b100111 >
b101 =
14
#78000
04
#79000
b101000 >
b110 =
14
#80000
04
#81000
b101001 >
b111 =
14
#82000
04
#83000
b101010 >
b1000 =
14
#84000
04
#85000
b101011 >
b1001 =
14
#86000
04
#87000
b101100 >
b1010 =
14
#88000
04
#89000
b101101 >
b1011 =
14
#90000
04
#91000
b101110 >
b1100 =
14
#92000
04
#93000
b101111 >
b1101 =
14
#94000
04
#95000
b110000 >
b1110 =
14
#96000
04
#97000
b110001 >
b1111 =
14
#98000
04
#99000
b110010 >
b10000 =
14
#100000
04
#101000
0&
0)
x?
xN
b110011 >
1(
b0 =
14
#102000
04
#103000
b110100 >
b1 =
14
#104000
04
#105000
b110101 >
b10 =
14
#106000
04
#107000
b110110 >
b11 =
14
#108000
04
#109000
b110111 >
b100 =
14
#110000
04
#111000
b111000 >
b101 =
14
#112000
04
#113000
b111001 >
b110 =
14
#114000
04
#115000
b111010 >
b111 =
14
#116000
04
#117000
b111011 >
b1000 =
14
#118000
04
#119000
b111100 >
b1001 =
14
#120000
04
#121000
b111101 >
b1010 =
14
#122000
04
#123000
b111110 >
b1011 =
14
#124000
04
#125000
b111111 >
b1100 =
14
#126000
04
#127000
b1000000 >
b1101 =
14
#128000
04
#129000
b1000001 >
b1110 =
14
#130000
04
#131000
b1000010 >
b1111 =
14
#132000
04
#133000
b1000011 >
b10000 =
14
#134000
04
#135000
b1000100 >
0(
b0 =
14
#136000
04
#137000
b1000101 >
b1 =
14
#138000
04
#139000
b1000110 >
b10 =
14
#140000
04
#141000
b1000111 >
b11 =
14
#142000
04
#143000
b1001000 >
b100 =
14
#144000
04
#145000
b1001001 >
b101 =
14
#146000
04
#147000
b1001010 >
b110 =
14
#148000
04
#149000
b1001011 >
b111 =
14
#150000
04
#151000
b1001100 >
b1000 =
14
#152000
04
#153000
b1001101 >
b1001 =
14
#154000
04
#155000
b1001110 >
b1010 =
14
#156000
04
#157000
b1001111 >
b1011 =
14
#158000
04
#159000
b1010000 >
b1100 =
14
#160000
04
#161000
b1010001 >
b1101 =
14
#162000
04
#163000
b1010010 >
b1110 =
14
#164000
04
#165000
b1010011 >
b1111 =
14
#166000
04
#167000
b1010100 >
b10000 =
14
#168000
04
#169000
b1010101 >
1(
b0 =
14
#170000
04
#171000
b1010110 >
b1 =
14
#172000
04
#173000
b1010111 >
b10 =
14
#174000
04
#175000
b1011000 >
b11 =
14
#176000
04
#177000
b1011001 >
b100 =
14
#178000
04
#179000
b1011010 >
b101 =
14
#180000
04
#181000
b1011011 >
b110 =
14
#182000
04
#183000
b1011100 >
b111 =
14
#184000
04
#185000
b1011101 >
b1000 =
14
#186000
04
#187000
b1011110 >
b1001 =
14
#188000
04
#189000
b1011111 >
b1010 =
14
#190000
04
#191000
b1100000 >
b1011 =
14
#192000
04
#193000
b1100001 >
b1100 =
14
#194000
04
#195000
b1100010 >
b1101 =
14
#196000
04
#197000
b1100011 >
b1110 =
14
#198000
04
#199000
b1100100 >
b1111 =
14
#200000
04
#201000
b1100101 >
b10000 =
14
#202000
04
#203000
b1100110 >
0(
b0 =
14
#204000
04
#205000
b1100111 >
b1 =
14
#206000
04
#207000
b1101000 >
b10 =
14
#208000
04
#209000
b1101001 >
b11 =
14
#210000
04
#211000
b1101010 >
b100 =
14
#212000
04
#213000
b1101011 >
b101 =
14
#214000
04
#215000
b1101100 >
b110 =
14
#216000
04
#217000
b1101101 >
b111 =
14
#218000
04
#219000
b1101110 >
b1000 =
14
#220000
04
#221000
b1101111 >
b1001 =
14
#222000
04
#223000
b1110000 >
b1010 =
14
#224000
04
#225000
b1110001 >
b1011 =
14
#226000
04
#227000
b1110010 >
b1100 =
14
#228000
04
#229000
b1110011 >
b1101 =
14
#230000
04
#231000
b1110100 >
b1110 =
14
#232000
04
#233000
b1110101 >
b1111 =
14
#234000
04
#235000
b1110110 >
b10000 =
14
#236000
04
#237000
b1110111 >
1(
b0 =
14
#238000
04
#239000
b1111000 >
b1 =
14
#240000
04
#241000
b1111001 >
b10 =
14
#242000
04
#243000
b1111010 >
b11 =
14
#244000
04
#245000
b1111011 >
b100 =
14
#246000
04
#247000
b1111100 >
b101 =
14
#248000
04
#249000
b1111101 >
b110 =
14
#250000
04
#251000
b1111110 >
b111 =
14
#252000
04
#253000
b1111111 >
b1000 =
14
#254000
04
#255000
b10000000 >
b1001 =
14
#256000
04
#257000
b10000001 >
b1010 =
14
#258000
04
#259000
b10000010 >
b1011 =
14
#260000
04
#261000
b10000011 >
b1100 =
14
#262000
04
#263000
b10000100 >
b1101 =
14
#264000
04
#265000
b10000101 >
b1110 =
14
#266000
04
#267000
b10000110 >
b1111 =
14
#268000
04
#269000
b10000111 >
b10000 =
14
#270000
04
#271000
b10001000 >
0(
b0 =
14
#272000
04
#273000
b10001001 >
b1 =
14
#274000
04
#275000
b10001010 >
b10 =
14
#276000
04
#277000
b10001011 >
b11 =
14
#278000
04
#279000
b10001100 >
b100 =
14
#280000
04
#281000
b10001101 >
b101 =
14
#282000
04
#283000
b10001110 >
b110 =
14
#284000
04
#285000
b10001111 >
b111 =
14
#286000
04
#287000
b10010000 >
b1000 =
14
#288000
04
#289000
b10010001 >
b1001 =
14
#290000
04
#291000
b10010010 >
b1010 =
14
#292000
04
#293000
b10010011 >
b1011 =
14
#294000
04
#295000
b10010100 >
b1100 =
14
#296000
04
#297000
b10010101 >
b1101 =
14
#298000
04
#299000
b10010110 >
b1110 =
14
#300000
04
#301000
b10010111 >
b1111 =
14
#302000
04
#303000
b10011000 >
b10000 =
14
#304000
04
#305000
b10011001 >
1(
b0 =
14
#306000
04
#307000
b10011010 >
b1 =
14
#308000
04
#309000
b10011011 >
b10 =
14
#310000
04
#311000
b10011100 >
b11 =
14
#312000
04
#313000
b10011101 >
b100 =
14
#314000
04
#315000
b10011110 >
b101 =
14
#316000
04
#317000
b10011111 >
b110 =
14
#318000
04
#319000
b10100000 >
b111 =
14
#320000
04
#321000
b10100001 >
b1000 =
14
#322000
04
#323000
b10100010 >
b1001 =
14
#324000
04
#325000
b10100011 >
b1010 =
14
#326000
04
#327000
b10100100 >
b1011 =
14
#328000
04
#329000
b10100101 >
b1100 =
14
#330000
04
#331000
b10100110 >
b1101 =
14
#332000
04
#333000
b10100111 >
b1110 =
14
#334000
04
#335000
b10101000 >
b1111 =
14
#336000
04
#337000
b10101001 >
b10000 =
14
#338000
04
#339000
b10101010 >
0(
b0 =
14
#340000
04
#341000
b10101011 >
b1 =
14
#342000
04
#343000
b10101100 >
b10 =
14
#344000
04
#345000
b10101101 >
b11 =
14
#346000
04
#347000
b10101110 >
b100 =
14
#348000
04
#349000
b10101111 >
b101 =
14
#350000
04
#351000
b10110000 >
b110 =
14
#352000
04
#353000
b10110001 >
b111 =
14
#354000
04
#355000
b10110010 >
b1000 =
14
#356000
04
#357000
b10110011 >
b1001 =
14
#358000
04
#359000
b10110100 >
b1010 =
14
#360000
04
#361000
b10110101 >
b1011 =
14
#362000
04
#363000
b10110110 >
b1100 =
14
#364000
04
#365000
b10110111 >
b1101 =
14
#366000
04
#367000
b10111000 >
b1110 =
14
#368000
04
#369000
b10111001 >
b1111 =
14
#370000
04
#371000
b10111010 >
b10000 =
14
#372000
04
#373000
b10111011 >
1(
b0 =
14
#374000
04
#375000
b10111100 >
b1 =
14
#376000
04
#377000
b10111101 >
b10 =
14
#378000
04
#379000
b10111110 >
b11 =
14
#380000
04
#381000
b10111111 >
b100 =
14
#382000
04
#383000
b11000000 >
b101 =
14
#384000
04
#385000
b11000001 >
b110 =
14
#386000
04
#387000
b11000010 >
b111 =
14
#388000
04
#389000
b11000011 >
b1000 =
14
#390000
04
#391000
b11000100 >
b1001 =
14
#392000
04
#393000
b11000101 >
b1010 =
14
#394000
04
#395000
b11000110 >
b1011 =
14
#396000
04
#397000
b11000111 >
b1100 =
14
#398000
04
#399000
b11001000 >
b1101 =
14
#400000
04
#401000
b11001001 >
b1110 =
14
#402000
04
#403000
b11001010 >
b1111 =
14
#404000
04
#405000
b11001011 >
b10000 =
14
#406000
04
#407000
b11001100 >
0(
b0 =
14
#408000
04
#409000
b11001101 >
b1 =
14
#410000
04
#411000
b11001110 >
b10 =
14
#412000
04
#413000
b11001111 >
b11 =
14
#414000
04
#415000
b11010000 >
b100 =
14
#416000
04
#417000
b11010001 >
b101 =
14
#418000
04
#419000
b11010010 >
b110 =
14
#420000
04
#421000
b11010011 >
b111 =
14
#422000
04
#423000
b11010100 >
b1000 =
14
#424000
04
#425000
b11010101 >
b1001 =
14
#426000
04
#427000
b11010110 >
b1010 =
14
#428000
04
#429000
b11010111 >
b1011 =
14
#430000
04
#431000
b11011000 >
b1100 =
14
#432000
04
#433000
b11011001 >
b1101 =
14
#434000
04
#435000
b11011010 >
b1110 =
14
#436000
04
#437000
b11011011 >
b1111 =
14
#438000
04
#439000
b11011100 >
b10000 =
14
#440000
04
#441000
b11011101 >
1(
b0 =
14
#442000
04
#443000
b11011110 >
b1 =
14
#444000
04
#445000
b11011111 >
b10 =
14
#446000
04
#447000
b11100000 >
b11 =
14
#448000
04
#449000
b11100001 >
b100 =
14
#450000
04
#451000
b11100010 >
b101 =
14
#452000
04
#453000
b11100011 >
b110 =
14
#454000
04
#455000
b11100100 >
b111 =
14
#456000
04
#457000
b11100101 >
b1000 =
14
#458000
04
#459000
b11100110 >
b1001 =
14
#460000
04
#461000
b11100111 >
b1010 =
14
#462000
04
#463000
b11101000 >
b1011 =
14
#464000
04
#465000
b11101001 >
b1100 =
14
#466000
04
#467000
b11101010 >
b1101 =
14
#468000
04
#469000
b11101011 >
b1110 =
14
#470000
04
#471000
b11101100 >
b1111 =
14
#472000
04
#473000
b11101101 >
b10000 =
14
#474000
04
#475000
b11101110 >
0(
b0 =
14
#476000
04
#477000
b11101111 >
b1 =
14
#478000
04
#479000
b11110000 >
b10 =
14
#480000
04
#481000
b11110001 >
b11 =
14
#482000
04
#483000
b11110010 >
b100 =
14
#484000
04
#485000
b11110011 >
b101 =
14
#486000
04
#487000
b11110100 >
b110 =
14
#488000
04
#489000
b11110101 >
b111 =
14
#490000
04
#491000
b11110110 >
b1000 =
14
#492000
04
#493000
b11110111 >
b1001 =
14
#494000
04
#495000
b11111000 >
b1010 =
14
#496000
04
#497000
b11111001 >
b1011 =
14
#498000
04
#499000
b11111010 >
b1100 =
14
#500000
04
#501000
b11111011 >
b1101 =
14
#502000
04
#503000
b11111100 >
b1110 =
14
#504000
04
#505000
b11111101 >
b1111 =
14
#506000
04
#507000
b11111110 >
b10000 =
14
#508000
04
#509000
b11111111 >
1(
b0 =
14
#510000
04
#511000
b100000000 >
b1 =
14
#512000
04
#513000
b100000001 >
b10 =
14
#514000
04
#515000
b100000010 >
b11 =
14
#516000
04
#517000
b100000011 >
b100 =
14
#518000
04
#519000
b100000100 >
b101 =
14
#520000
04
#521000
b100000101 >
b110 =
14
#522000
04
#523000
b100000110 >
b111 =
14
#524000
04
#525000
b100000111 >
b1000 =
14
#526000
04
#527000
b100001000 >
b1001 =
14
#528000
04
#529000
b100001001 >
b1010 =
14
#530000
04
#531000
b100001010 >
b1011 =
14
#532000
04
#533000
b100001011 >
b1100 =
14
#534000
04
#535000
b100001100 >
b1101 =
14
#536000
04
#537000
b100001101 >
b1110 =
14
#538000
04
#539000
b100001110 >
b1111 =
14
#540000
04
#541000
b100001111 >
b10000 =
14
#542000
04
#543000
b1 \
0$
0"
1!
1#
b0 >
0(
b0 =
14
#544000
04
#545000
b1 >
b1 =
14
#546000
04
#547000
b10 >
b10 =
14
#548000
04
#549000
b11 >
b11 =
14
#550000
04
#551000
b100 >
b100 =
14
#552000
04
#553000
b101 >
b101 =
14
#554000
04
#555000
b110 >
b110 =
14
#556000
04
#557000
b111 >
b111 =
14
#558000
04
#559000
b1000 >
b1000 =
14
#560000
04
#561000
b1001 >
b1001 =
14
#562000
04
#563000
b1010 >
b1010 =
14
#564000
04
#565000
b1011 >
b1011 =
14
#566000
04
#567000
b1100 >
b1100 =
14
#568000
04
#569000
b1101 >
b1101 =
14
#570000
04
#571000
b1110 >
b1110 =
14
#572000
04
#573000
b1111 >
b1111 =
14
#574000
04
#575000
b10000 >
b10000 =
14
#576000
04
#577000
1M
b10001 >
1(
b0 =
14
#578000
04
#579000
b10010 >
b1 =
14
#580000
04
#581000
b10011 >
b10 =
14
#582000
04
#583000
b10100 >
b11 =
14
#584000
04
#585000
b10101 >
b100 =
14
#586000
04
#587000
b10110 >
b101 =
14
#588000
04
#589000
b10111 >
b110 =
14
#590000
04
#591000
b11000 >
b111 =
14
#592000
04
#593000
b11001 >
b1000 =
14
#594000
04
#595000
b11010 >
b1001 =
14
#596000
04
#597000
b11011 >
b1010 =
14
#598000
04
#599000
b11100 >
b1011 =
14
#600000
04
#601000
b11101 >
b1100 =
14
#602000
04
#603000
b11110 >
b1101 =
14
#604000
04
#605000
b11111 >
b1110 =
14
#606000
04
#607000
b100000 >
b1111 =
14
#608000
04
#609000
b100001 >
b10000 =
14
#610000
04
#611000
b100010 >
0(
b0 =
14
#612000
04
#613000
b100011 >
b1 =
14
#614000
04
#615000
b100100 >
b10 =
14
#616000
04
#617000
b100101 >
b11 =
14
#618000
04
#619000
b100110 >
b100 =
14
#620000
04
#621000
b100111 >
b101 =
14
#622000
04
#623000
b101000 >
b110 =
14
#624000
04
#625000
b101001 >
b111 =
14
#626000
04
#627000
b101010 >
b1000 =
14
#628000
04
#629000
b101011 >
b1001 =
14
#630000
04
#631000
b101100 >
b1010 =
14
#632000
04
#633000
b101101 >
b1011 =
14
#634000
04
#635000
b101110 >
b1100 =
14
#636000
04
#637000
b101111 >
b1101 =
14
#638000
04
#639000
b110000 >
b1110 =
14
#640000
04
#641000
b110001 >
b1111 =
14
#642000
04
#643000
b110010 >
b10000 =
14
#644000
04
#645000
1?
1N
b110011 >
1(
b0 =
14
#646000
04
#647000
b110100 >
b1 =
14
#648000
04
#649000
b110101 >
b10 =
14
#650000
04
#651000
b110110 >
b11 =
14
#652000
04
#653000
b110111 >
b100 =
14
#654000
04
#655000
b111000 >
b101 =
14
#656000
04
#657000
b111001 >
b110 =
14
#658000
04
#659000
b111010 >
b111 =
14
#660000
04
#661000
b111011 >
b1000 =
14
#662000
04
#663000
b111100 >
b1001 =
14
#664000
04
#665000
b111101 >
b1010 =
14
#666000
04
#667000
b111110 >
b1011 =
14
#668000
04
#669000
b111111 >
b1100 =
14
#670000
04
#671000
b1000000 >
b1101 =
14
#672000
04
#673000
b1000001 >
b1110 =
14
#674000
04
#675000
b1000010 >
b1111 =
14
#676000
04
#677000
b1000011 >
b10000 =
14
#678000
04
#679000
b1000100 >
0(
b0 =
14
#680000
04
#681000
b1000101 >
b1 =
14
#682000
04
#683000
b1000110 >
b10 =
14
#684000
04
#685000
b1000111 >
b11 =
14
#686000
04
#687000
b1001000 >
b100 =
14
#688000
04
#689000
b1001001 >
b101 =
14
#690000
04
#691000
b1001010 >
b110 =
14
#692000
04
#693000
b1001011 >
b111 =
14
#694000
04
#695000
b1001100 >
b1000 =
14
#696000
04
#697000
b1001101 >
b1001 =
14
#698000
04
#699000
b1001110 >
b1010 =
14
#700000
04
#701000
b1001111 >
b1011 =
14
#702000
04
#703000
b1010000 >
b1100 =
14
#704000
04
#705000
b1010001 >
b1101 =
14
#706000
04
#707000
b1010010 >
b1110 =
14
#708000
04
#709000
b1010011 >
b1111 =
14
#710000
04
#711000
b1010100 >
b10000 =
14
#712000
04
#713000
b1010101 >
1(
b0 =
14
#714000
04
#715000
b1010110 >
b1 =
14
#716000
04
#717000
b1010111 >
b10 =
14
#718000
04
#719000
b1011000 >
b11 =
14
#720000
04
#721000
b1011001 >
b100 =
14
#722000
04
#723000
b1011010 >
b101 =
14
#724000
04
#725000
b1011011 >
b110 =
14
#726000
04
#727000
b1011100 >
b111 =
14
#728000
04
#729000
b1011101 >
b1000 =
14
#730000
04
#731000
b1011110 >
b1001 =
14
#732000
04
#733000
b1011111 >
b1010 =
14
#734000
04
#735000
b1100000 >
b1011 =
14
#736000
04
#737000
b1100001 >
b1100 =
14
#738000
04
#739000
b1100010 >
b1101 =
14
#740000
04
#741000
b1100011 >
b1110 =
14
#742000
04
#743000
b1100100 >
b1111 =
14
#744000
04
#745000
b1100101 >
b10000 =
14
#746000
04
#747000
b1100110 >
0(
b0 =
14
#748000
04
#749000
b1100111 >
b1 =
14
#750000
04
#751000
b1101000 >
b10 =
14
#752000
04
#753000
b1101001 >
b11 =
14
#754000
04
#755000
b1101010 >
b100 =
14
#756000
04
#757000
b1101011 >
b101 =
14
#758000
04
#759000
b1101100 >
b110 =
14
#760000
04
#761000
b1101101 >
b111 =
14
#762000
04
#763000
b1101110 >
b1000 =
14
#764000
04
#765000
b1101111 >
b1001 =
14
#766000
04
#767000
b1110000 >
b1010 =
14
#768000
04
#769000
b1110001 >
b1011 =
14
#770000
04
#771000
b1110010 >
b1100 =
14
#772000
04
#773000
b1110011 >
b1101 =
14
#774000
04
#775000
b1110100 >
b1110 =
14
#776000
04
#777000
b1110101 >
b1111 =
14
#778000
04
#779000
b1110110 >
b10000 =
14
#780000
04
#781000
b1110111 >
1(
b0 =
14
#782000
04
#783000
b1111000 >
b1 =
14
#784000
04
#785000
b1111001 >
b10 =
14
#786000
04
#787000
b1111010 >
b11 =
14
#788000
04
#789000
b1111011 >
b100 =
14
#790000
04
#791000
b1111100 >
b101 =
14
#792000
04
#793000
b1111101 >
b110 =
14
#794000
04
#795000
b1111110 >
b111 =
14
#796000
04
#797000
b1111111 >
b1000 =
14
#798000
04
#799000
b10000000 >
b1001 =
14
#800000
04
#801000
b10000001 >
b1010 =
14
#802000
04
#803000
b10000010 >
b1011 =
14
#804000
04
#805000
b10000011 >
b1100 =
14
#806000
04
#807000
b10000100 >
b1101 =
14
#808000
04
