uart/header/parameter.vh
`ifndef parameter_vh
`define parameter_vh

`define unit_1ns 1_000_000_000

`define clk100MHz 100_000_000
`define clk200MHz 200_000_000
`define clk300MHz 300_000_000
`define clk400MHz 400_000_000
`define clk500MHz 500_000_000
`define clk1GHz  1000_000_000

`define bitwidth5 5
`define bitwidth6 6
`define bitwidth7 7
`define bitwidth8 8

`define baud9600    9_600
`define baud19200   19_200
`define baud38400   38_400
`define baud57600   57_600
`define baud115200  115_200
`define baud230400  230_400
`define baud460800  460_800
`define baud921600  921_600

`define baud_slow   9600
`define baud_mid    115200
`define baud_fast   921600

`endif

uart/rtl/receive_rev.v
`timescale 1ns/1ps

module receive#(
	parameter bits =8,
	parameter oversample =16)(
	clk, en, in, rst,
	out, done, busy, error,
	rts, read);
	localparam bitsWidth =$clog2(bits);
	localparam osrWidth  =$clog2(oversample);
	localparam osrHalf   =oversample/2;

	localparam reset     =3'd0;
	localparam idle      =3'd1;
	localparam startBit  =3'd2;
	localparam dataBits  =3'd3;
	localparam stopBit   =3'd4;

	localparam [(bitsWidth-1):0] last =(bits-1);

	input wire clk, en, in, rst;
	output reg [(bits-1):0] out;
	output reg done, busy, error;
//	output reg valid;
	reg valid;
	output wire rts;
	input wire read;

	reg [2:0]             state       =reset;
	reg [(bits-1):0]      data        =1'd0;
	reg [(bitsWidth-1):0] bitIndex    =1'd0;
	reg [(osrWidth-1):0]  sampleCount =1'd0;

	//Two registers for mitigating Metastability
	reg inFF0 =1'b1, inFF1 =1'b1;
    reg rxPrev =1'b1;
	wire rx =inFF1;
	wire rxFall =rxPrev&&(!rx);

	assign rts =en&&(state==idle)&&(!valid);

	always@(posedge clk)begin
		
		inFF0 <= in;
		inFF1 <= inFF0;

		done <=1'b0;
		error <=1'b0;

		if (rst)begin
			state <=idle;
			out   <=1'd0;
//			done  <=1'b0;
			busy  <=1'b0;
//			error <=1'b0;
			data  <=1'd0;
			sampleCount <=1'd0;
			bitIndex <=1'd0;
			valid <=1'b0;
		end
		else begin
			case(state)
				reset:begin
					out   <=1'd0;
					done  <=1'b0;
					busy  <=1'b0;
					error <=1'b0;
					data  <=1'd0;
					state <=idle;
					valid <=1'b0;
				end
				idle:begin
					busy     <=1'b0;
					bitIndex <=1'd0;
					data     <=1'd0;
//					error    <=1'b0;
//					done     <=1'b0;
					sampleCount <=1'd0;
					if(read) valid <=1'b0;
					if(en&&(!valid)&&(rxFall))begin
					//if(en&(~rx))begin
						busy <=1'b1;
						state <=startBit;
					end
				end
				startBit:begin
					busy <=1'b1;
					if(sampleCount==(osrHalf-1))begin
						sampleCount <=1'd0;
						if(~rx)begin
							bitIndex <=1'd0;
							state    <=dataBits;
						end
						else begin
							busy  <=1'b0;
							state <=idle;
						end
					end
					else sampleCount <=(sampleCount+1'b1);
				end
				dataBits:begin
					busy <=1'b1;
					if(sampleCount==(oversample-1))begin
						sampleCount <=1'd0;
						data[bitIndex] <=rx;
						if(bitIndex==last)begin
							state <=stopBit;
						end
						else bitIndex <=(bitIndex+1'b1);
					end
					else sampleCount <=(sampleCount+1'b1);
				end
				stopBit:begin
					busy <=1'b1;
					if(sampleCount==(oversample-1))begin
						sampleCount <=1'd0;
						busy <=1'b0;
						if(!rx) error <=1'b1;
						else if(valid) error <=1'b1;
						else begin
							out <=data;
							done <=1'b1;
							valid <=1'b1;
						end
						state<=idle;
					end
					else sampleCount <=(sampleCount+1'b1);
				end
				default: state <=idle;
			endcase
		end
	end
endmodule

uart/rtl/transmit.v
`timescale 1ns/1ps

module transmit #(
	parameter bits =8)(
	clk, en, start,
	in,
	out, done, busy,
	cts);
	localparam bitsWidth =$clog2(bits);
	localparam reset     =3'd0;
	localparam idle      =3'd1;
	localparam startBit  =3'd2;
	localparam dataBits  =3'd3;
	localparam stopBit   =3'd4;

	input wire clk, en, start;
	input wire [(bits-1):0] in;
	output reg out, done, busy;
	input wire cts;

	reg [3:0] state =reset;
	reg [(bits-1):0] data =0;

	reg [(bitsWidth-1):0] bitIndex =0; 

	always@(posedge clk)begin
		case(state)
			reset:begin
				out <=1'b1;
				done <=1'b0;
				busy <=1'b0;
				data <=1'd0;
				bitIndex <=1'd0;
				state <= idle;
			end
			idle:begin 
				//if out becomes 0, Transmission starts
				out <=1'b1;
				done <=1'b0;
				bitIndex <=1'd0;
				data <=1'd0;
				if(start&en&cts) state <=startBit;
			end
			startBit:begin
				data <=in;
				out <=1'b0;
				busy <=1'b1;
				state <=dataBits;
			end
			dataBits:begin
				out <=data[bitIndex];
				//if(&bitIndex)begin
				if(bitIndex==(bits-1))begin
					bitIndex <=0;
					state <=stopBit;
				end
				else bitIndex <=(bitIndex+1'b1);
			end
			stopBit:begin
				done <=1'b1;
				data <='b0;
				out <=1'b1;
				busy <=1'b0;
				state <=idle;
			end
			default: state <=reset;
		endcase
	end
endmodule

uart/rtl/baudrategen.v
`timescale 1ns/1ps

module baudrategen#(
	parameter clock =100_000_000,
	parameter baudrate =115_200,
	parameter oversample =16)(
	input wire clk,
	output reg RXclk, output reg TXclk
	);
	localparam maxRateRX =clock/(2*baudrate*oversample);
	localparam maxRateTX =clock/(2*baudrate);
	localparam RXcountWidth =$clog2(maxRateRX+1);
	localparam TXcountWidth =$clog2(maxRateTX+1);

	reg [(RXcountWidth-1):0] RXcount=0;
	reg [(TXcountWidth-1):0] TXcount=0;

	initial begin
		RXclk =1'b0;
		TXclk =1'b0;
	end

	always@(posedge clk)begin
		if(RXcount==(maxRateRX))begin
			RXcount <=0;
			RXclk <=~RXclk;
		end
		else RXcount <=(RXcount +1'b1);
		if(TXcount==(maxRateTX))begin
			TXcount <=0;
			TXclk <=~TXclk;
		end
		else TXcount <=(TXcount+1'b1);
	end
endmodule

uart/testbench/receive_rev/tb_receive_rev.v
`include "parameter.vh"
`include "transmit.v"
`include "baudrategen.v"
`include "receive_rev.v"
`timescale 1ns/1ps

module tb_receive_rev;
	parameter integer clock =`clk500MHz;
	parameter integer latency = (1_000_000_000/(2*clock));
	parameter integer baudrate =`baud_fast;
	parameter integer bitwidth =`bitwidth8;
	parameter integer oversample =16;

	localparam integer clockTick =(clock/baudrate)*2*latency;

	reg clk =1'b0;
	wire RXclk, TXclk;
	
	reg TXen =1'b1;
	reg TXstart =0;
	reg [(bitwidth-1):0] in ='0;

	wire TXout;
	wire TXdone;
	wire TXbusy;
	
	reg RXen =1'b1;
	reg RXrst =1'b0;
	wire [(bitwidth-1):0] RXout;
	wire RXdone, RXbusy, RXerror;
	
	wire rts;

	baudrategen #(clock,baudrate,16) baudgen(clk, RXclk, TXclk);

	transmit #(bitwidth) transmit0(TXclk, TXen, TXstart, in, TXout, TXdone, TXbusy, rts);
	receive  #(bitwidth) receive0(RXclk, RXen, TXout, RXrst, RXout, RXdone, RXbusy, RXerror, rts, {1'b1});

	task test;
		input [(bitwidth-1):0] in_t;
		in <= in_t;
		#clockTick TXstart <=1'b1;
		#clockTick TXstart <=1'b0;
		#clockTick;
		#(bitwidth*clockTick);
		#clockTick;
		#clockTick;
	endtask
	
	initial begin
		$dumpfile("out.vcd");
		$dumpvars(0,tb_receive_rev);
		test(8'h55);
		test(8'h96);
		test(8'h47);
		test(8'h0c);
		$finish;
	end
	always #latency clk =~clk;
endmodule

uart/testbench/receive_rev/out.vcd
$date
	Tue Mar 24 21:29:21 2026
$end
$version
	Icarus Verilog
$end
$timescale
	1ps
$end
$scope module tb_receive_rev $end
$var wire 1 ! rts $end
$var wire 1 " TXout $end
$var wire 1 # TXdone $end
$var wire 1 $ TXclk $end
$var wire 1 % TXbusy $end
$var wire 8 & RXout [7:0] $end
$var wire 1 ' RXerror $end
$var wire 1 ( RXdone $end
$var wire 1 ) RXclk $end
$var wire 1 * RXbusy $end
$var parameter 32 + baudrate $end
$var parameter 32 , bitwidth $end
$var parameter 32 - clock $end
$var parameter 32 . clockTick $end
$var parameter 32 / latency $end
$var parameter 32 0 oversample $end
$var reg 1 1 RXen $end
$var reg 1 2 RXrst $end
$var reg 1 3 TXen $end
$var reg 1 4 TXstart $end
$var reg 1 5 clk $end
$var reg 8 6 in [7:0] $end
$scope module baudgen $end
$var wire 1 5 clk $end
$var parameter 32 7 RXcountWidth $end
$var parameter 32 8 TXcountWidth $end
$var parameter 32 9 baudrate $end
$var parameter 32 : clock $end
$var parameter 96 ; maxRateRX $end
$var parameter 64 < maxRateTX $end
$var parameter 32 = oversample $end
$var reg 1 ) RXclk $end
$var reg 5 > RXcount [4:0] $end
$var reg 1 $ TXclk $end
$var reg 9 ? TXcount [8:0] $end
$upscope $end
$scope module receive0 $end
$var wire 1 ) clk $end
$var wire 1 1 en $end
$var wire 1 @ read $end
$var wire 1 2 rst $end
$var wire 1 ! rts $end
$var wire 1 A rx $end
$var wire 1 B rxFall $end
$var wire 1 " in $end
$var parameter 32 C bits $end
$var parameter 32 D bitsWidth $end
$var parameter 3 E dataBits $end
$var parameter 3 F idle $end
$var parameter 3 G last $end
$var parameter 32 H osrHalf $end
$var parameter 32 I osrWidth $end
$var parameter 32 J oversample $end
$var parameter 3 K reset $end
$var parameter 3 L startBit $end
$var parameter 3 M stopBit $end
$var reg 3 N bitIndex [2:0] $end
$var reg 1 * busy $end
$var reg 8 O data [7:0] $end
$var reg 1 ( done $end
$var reg 1 ' error $end
$var reg 1 P inFF0 $end
$var reg 1 A inFF1 $end
$var reg 8 Q out [7:0] $end
$var reg 1 R rxPrev $end
$var reg 4 S sampleCount [3:0] $end
$var reg 3 T state [2:0] $end
$var reg 1 U valid $end
$upscope $end
$scope module transmit0 $end
$var wire 1 $ clk $end
$var wire 1 ! cts $end
$var wire 1 3 en $end
$var wire 8 V in [7:0] $end
$var wire 1 4 start $end
$var parameter 32 W bits $end
$var parameter 32 X bitsWidth $end
$var parameter 3 Y dataBits $end
$var parameter 3 Z idle $end
$var parameter 3 [ reset $end
$var parameter 3 \ startBit $end
$var parameter 3 ] stopBit $end
$var reg 3 ^ bitIndex [2:0] $end
$var reg 1 % busy $end
$var reg 8 _ data [7:0] $end
$var reg 1 # done $end
$var reg 1 " out $end
$var reg 4 ` state [3:0] $end
$upscope $end
$scope task test $end
$var reg 8 a in_t [7:0] $end
$upscope $end
$upscope $end
$enddefinitions $end
$comment Show the parameter values. $end
$dumpall
b100 ]
b10 \
b0 [
b1 Z
b11 Y
b11 X
b1000 W
b100 M
b10 L
b0 K
b10000 J
b100 I
b1000 H
b111 G
b1 F
b11 E
b11 D
b1000 C
b10000 =
b100001111 <
b10000 ;
b11101110011010110010100000000 :
b11100001000000000000 9
b1001 8
b101 7
b10000 0
b1 /
b10000111100 .
b11101110011010110010100000000 -
b1000 ,
b11100001000000000000 +
$end
#0
$dumpvars
b1010101 a
b0 `
b0 _
b0 ^
b1010101 V
xU
b0 T
b0 S
1R
bx Q
1P
b0 O
b0 N
0B
1A
1@
b0 ?
b0 >
b1010101 6
05
04
13
02
11
x*
0)
x(
x'
bx &
x%
0$
x#
x"
0!
$end
#1000
b1 ?
b1 >
15
#2000
05
#3000
b10 ?
b10 >
15
#4000
05
#5000
b11 ?
b11 >
15
#6000
05
#7000
b100 ?
b100 >
15
#8000
05
#9000
b101 ?
b101 >
15
#10000
05
#11000
b110 ?
b110 >
15
#12000
05
#13000
b111 ?
b111 >
15
#14000
05
#15000
b1000 ?
b1000 >
15
#16000
05
#17000
b1001 ?
b1001 >
15
#18000
05
#19000
b1010 ?
b1010 >
15
#20000
05
#21000
b1011 ?
b1011 >
15
#22000
05
#23000
b1100 ?
b1100 >
15
#24000
05
#25000
b1101 ?
b1101 >
15
#26000
05
#27000
b1110 ?
b1110 >
15
#28000
05
#29000
b1111 ?
b1111 >
15
#30000
05
#31000
b10000 ?
b10000 >
15
#32000
05
#33000
1!
0U
b1 T
0*
b0 &
b0 Q
0'
0(
xP
b10001 ?
1)
b0 >
15
#34000
05
#35000
b10010 ?
b1 >
15
#36000
05
#37000
b10011 ?
b10 >
15
#38000
05
#39000
b10100 ?
b11 >
15
#40000
05
#41000
b10101 ?
b100 >
15
#42000
05
#43000
b10110 ?
b101 >
15
#44000
05
#45000
b10111 ?
b110 >
15
#46000
05
#47000
b11000 ?
b111 >
15
#48000
05
#49000
b11001 ?
b1000 >
15
#50000
05
#51000
b11010 ?
b1001 >
15
#52000
05
#53000
b11011 ?
b1010 >
15
#54000
05
#55000
b11100 ?
b1011 >
15
#56000
05
#57000
b11101 ?
b1100 >
15
#58000
05
#59000
b11110 ?
b1101 >
15
#60000
05
#61000
b11111 ?
b1110 >
15
#62000
05
#63000
b100000 ?
b1111 >
15
#64000
05
#65000
b100001 ?
b10000 >
15
#66000
05
#67000
b100010 ?
0)
b0 >
15
#68000
05
#69000
b100011 ?
b1 >
15
#70000
05
#71000
b100100 ?
b10 >
15
#72000
05
#73000
b100101 ?
b11 >
15
#74000
05
#75000
b100110 ?
b100 >
15
#76000
05
#77000
b100111 ?
b101 >
15
#78000
05
#79000
b101000 ?
b110 >
15
#80000
05
#81000
b101001 ?
b111 >
15
#82000
05
#83000
b101010 ?
b1000 >
15
#84000
05
#85000
b101011 ?
b1001 >
15
#86000
05
#87000
b101100 ?
b1010 >
15
#88000
05
#89000
b101101 ?
b1011 >
15
#90000
05
#91000
b101110 ?
b1100 >
15
#92000
05
#93000
b101111 ?
b1101 >
15
#94000
05
#95000
b110000 ?
b1110 >
15
#96000
05
#97000
b110001 ?
b1111 >
15
#98000
05
#99000
b110010 ?
b10000 >
15
#100000
05
#101000
xB
xA
b110011 ?
1)
b0 >
15
#102000
05
#103000
b110100 ?
b1 >
15
#104000
05
#105000
b110101 ?
b10 >
15
#106000
05
#107000
b110110 ?
b11 >
15
#108000
05
#109000
b110111 ?
b100 >
15
#110000
05
#111000
b111000 ?
b101 >
15
#112000
05
#113000
b111001 ?
b110 >
15
#114000
05
#115000
b111010 ?
b111 >
15
#116000
05
#117000
b111011 ?
b1000 >
15
#118000
05
#119000
b111100 ?
b1001 >
15
#120000
05
#121000
b111101 ?
b1010 >
15
#122000
05
#123000
b111110 ?
b1011 >
15
#124000
05
#125000
b111111 ?
b1100 >
15
#126000
05
#127000
b1000000 ?
b1101 >
15
#128000
05
#129000
b1000001 ?
b1110 >
15
#130000
05
#131000
b1000010 ?
b1111 >
15
#132000
05
#133000
b1000011 ?
b10000 >
15
#134000
05
#135000
b1000100 ?
0)
b0 >
15
#136000
05
#137000
b1000101 ?
b1 >
15
#138000
05
#139000
b1000110 ?
b10 >
15
#140000
05
#141000
b1000111 ?
b11 >
15
#142000
05
#143000
b1001000 ?
b100 >
15
#144000
05
#145000
b1001001 ?
b101 >
15
#146000
05
#147000
b1001010 ?
b110 >
15
#148000
05
#149000
b1001011 ?
b111 >
15
#150000
05
#151000
b1001100 ?
b1000 >
15
#152000
05
#153000
b1001101 ?
b1001 >
15
#154000
05
#155000
b1001110 ?
b1010 >
15
#156000
05
#157000
b1001111 ?
b1011 >
15
#158000
05
#159000
b1010000 ?
b1100 >
15
#160000
05
#161000
b1010001 ?
b1101 >
15
#162000
05
#163000
b1010010 ?
b1110 >
15
#164000
05
#165000
b1010011 ?
b1111 >
15
#166000
05
#167000
b1010100 ?
b10000 >
15
#168000
05
#169000
b1010101 ?
1)
b0 >
15
#170000
05
#171000
b1010110 ?
b1 >
15
#172000
05
#173000
b1010111 ?
b10 >
15
#174000
05
#175000
b1011000 ?
b11 >
15
#176000
05
#177000
b1011001 ?
b100 >
15
#178000
05
#179000
b1011010 ?
b101 >
15
#180000
05
#181000
b1011011 ?
b110 >
15
#182000
05
#183000
b1011100 ?
b111 >
15
#184000
05
#185000
b1011101 ?
b1000 >
15
#186000
05
#187000
b1011110 ?
b1001 >
15
#188000
05
#189000
b1011111 ?
b1010 >
15
#190000
05
#191000
b1100000 ?
b1011 >
15
#192000
05
#193000
b1100001 ?
b1100 >
15
#194000
05
#195000
b1100010 ?
b1101 >
15
#196000
05
#197000
b1100011 ?
b1110 >
15
#198000
05
#199000
b1100100 ?
b1111 >
15
#200000
05
#201000
b1100101 ?
b10000 >
15
#202000
05
#203000
b1100110 ?
0)
b0 >
15
#204000
05
#205000
b1100111 ?
b1 >
15
#206000
05
#207000
b1101000 ?
b10 >
15
#208000
05
#209000
b1101001 ?
b11 >
15
#210000
05
#211000
b1101010 ?
b100 >
15
#212000
05
#213000
b1101011 ?
b101 >
15
#214000
05
#215000
b1101100 ?
b110 >
15
#216000
05
#217000
b1101101 ?
b111 >
15
#218000
05
#219000
b1101110 ?
b1000 >
15
#220000
05
#221000
b1101111 ?
b1001 >
15
#222000
05
#223000
b1110000 ?
b1010 >
15
#224000
05
#225000
b1110001 ?
b1011 >
15
#226000
05
#227000
b1110010 ?
b1100 >
15
#228000
05
#229000
b1110011 ?
b1101 >
15
#230000
05
#231000
b1110100 ?
b1110 >
15
#232000
05
#233000
b1110101 ?
b1111 >
15
#234000
05
#235000
b1110110 ?
b10000 >
15
#236000
05
#237000
b1110111 ?
1)
b0 >
15
#238000
05
#239000
b1111000 ?
b1 >
15
#240000
05
#241000
b1111001 ?
b10 >
15
#242000
05
#243000
b1111010 ?
b11 >
15
#244000
05
#245000
b1111011 ?
b100 >
15
#246000
05
#247000
b1111100 ?
b101 >
15
#248000
05
#249000
b1111101 ?
b110 >
15
#250000
05
#251000
b1111110 ?
b111 >
15
#252000
05
#253000
b1111111 ?
b1000 >
15
#254000
05
#255000
b10000000 ?
b1001 >
15
#256000
05
#257000
b10000001 ?
b1010 >
15
#258000
05
#259000
b10000010 ?
b1011 >
15
#260000
05
#261000
b10000011 ?
b1100 >
15
#262000
05
#263000
b10000100 ?
b1101 >
15
#264000
05
#265000
b10000101 ?
b1110 >
15
#266000
05
#267000
b10000110 ?
b1111 >
15
#268000
05
#269000
b10000111 ?
b10000 >
15
#270000
05
#271000
b10001000 ?
0)
b0 >
15
#272000
05
#273000
b10001001 ?
b1 >
15
#274000
05
#275000
b10001010 ?
b10 >
15
#276000
05
#277000
b10001011 ?
b11 >
15
#278000
05
#279000
b10001100 ?
b100 >
15
#280000
05
#281000
b10001101 ?
b101 >
15
#282000
05
#283000
b10001110 ?
b110 >
15
#284000
05
#285000
b10001111 ?
b111 >
15
#286000
05
#287000
b10010000 ?
b1000 >
15
#288000
05
#289000
b10010001 ?
b1001 >
15
#290000
05
#291000
b10010010 ?
b1010 >
15
#292000
05
#293000
b10010011 ?
b1011 >
15
#294000
05
#295000
b10010100 ?
b1100 >
15
#296000
05
#297000
b10010101 ?
b1101 >
15
#298000
05
#299000
b10010110 ?
b1110 >
15
#300000
05
#301000
b10010111 ?
b1111 >
15
#302000
05
#303000
b10011000 ?
b10000 >
15
#304000
05
#305000
b10011001 ?
1)
b0 >
15
#306000
05
#307000
b10011010 ?
b1 >
15
#308000
05
#309000
b10011011 ?
b10 >
15
#310000
05
#311000
b10011100 ?
b11 >
15
#312000
05
#313000
b10011101 ?
b100 >
15
#314000
05
#315000
b10011110 ?
b101 >
15
#316000
05
#317000
b10011111 ?
b110 >
15
#318000
05
#319000
b10100000 ?
b111 >
15
#320000
05
#321000
b10100001 ?
b1000 >
15
#322000
05
#323000
b10100010 ?
b1001 >
15
#324000
05
#325000
b10100011 ?
b1010 >
15
#326000
05
#327000
b10100100 ?
b1011 >
15
#328000
05
#329000
b10100101 ?
b1100 >
15
#330000
05
#331000
b10100110 ?
b1101 >
15
#332000
05
#333000
b10100111 ?
b1110 >
15
#334000
05
#335000
b10101000 ?
b1111 >
15
#336000
05
#337000
b10101001 ?
b10000 >
15
#338000
05
#339000
b10101010 ?
0)
b0 >
15
#340000
05
#341000
b10101011 ?
b1 >
15
#342000
05
#343000
b10101100 ?
b10 >
15
#344000
05
#345000
b10101101 ?
b11 >
15
#346000
05
#347000
b10101110 ?
b100 >
15
#348000
05
#349000
b10101111 ?
b101 >
15
#350000
05
#351000
b10110000 ?
b110 >
15
#352000
05
#353000
b10110001 ?
b111 >
15
#354000
05
#355000
b10110010 ?
b1000 >
15
#356000
05
#357000
b10110011 ?
b1001 >
15
#358000
05
#359000
b10110100 ?
b1010 >
15
#360000
05
#361000
b10110101 ?
b1011 >
15
#362000
05
#363000
b10110110 ?
b1100 >
15
#364000
05
#365000
b10110111 ?
b1101 >
15
#366000
05
#367000
b10111000 ?
b1110 >
15
#368000
05
#369000
b10111001 ?
b1111 >
15
#370000
05
#371000
b10111010 ?
b10000 >
15
#372000
05
#373000
b10111011 ?
1)
b0 >
15
#374000
05
#375000
b10111100 ?
b1 >
15
#376000
05
#377000
b10111101 ?
b10 >
15
#378000
05
#379000
b10111110 ?
b11 >
15
#380000
05
#381000
b10111111 ?
b100 >
15
#382000
05
#383000
b11000000 ?
b101 >
15
#384000
05
#385000
b11000001 ?
b110 >
15
#386000
05
#387000
b11000010 ?
b111 >
15
#388000
05
#389000
b11000011 ?
b1000 >
15
#390000
05
#391000
b11000100 ?
b1001 >
15
#392000
05
#393000
b11000101 ?
b1010 >
15
#394000
05
#395000
b11000110 ?
b1011 >
15
#396000
05
#397000
b11000111 ?
b1100 >
15
#398000
05
#399000
b11001000 ?
b1101 >
15
#400000
05
#401000
b11001001 ?
b1110 >
15
#402000
05
#403000
b11001010 ?
b1111 >
15
#404000
05
#405000
b11001011 ?
b10000 >
15
#406000
05
#407000
b11001100 ?
0)
b0 >
15
#408000
05
#409000
b11001101 ?
b1 >
15
#410000
05
#411000
b11001110 ?
b10 >
15
#412000
05
#413000
b11001111 ?
b11 >
15
#414000
05
#415000
b11010000 ?
b100 >
15
#416000
05
#417000
b11010001 ?
b101 >
15
#418000
05
#419000
b11010010 ?
b110 >
15
#420000
05
#421000
b11010011 ?
b111 >
15
#422000
05
#423000
b11010100 ?
b1000 >
15
#424000
05
#425000
b11010101 ?
b1001 >
15
#426000
05
#427000
b11010110 ?
b1010 >
15
#428000
05
#429000
b11010111 ?
b1011 >
15
#430000
05
#431000
b11011000 ?
b1100 >
15
#432000
05
#433000
b11011001 ?
b1101 >
15
#434000
05
#435000
b11011010 ?
b1110 >
15
#436000
05
#437000
b11011011 ?
b1111 >
15
#438000
05
#439000
b11011100 ?
b10000 >
15
#440000
05
#441000
b11011101 ?
1)
b0 >
15
#442000
05
#443000
b11011110 ?
b1 >
15
#444000
05
#445000
b11011111 ?
b10 >
15
#446000
05
#447000
b11100000 ?
b11 >
15
#448000
05
#449000
b11100001 ?
b100 >
15
#450000
05
#451000
b11100010 ?
b101 >
15
#452000
05
#453000
b11100011 ?
b110 >
15
#454000
05
#455000
b11100100 ?
b111 >
15
#456000
05
#457000
b11100101 ?
b1000 >
15
#458000
05
#459000
b11100110 ?
b1001 >
15
#460000
05
#461000
b11100111 ?
b1010 >
15
#462000
05
#463000
b11101000 ?
b1011 >
15
#464000
05
#465000
b11101001 ?
b1100 >
15
#466000
05
#467000
b11101010 ?
b1101 >
15
#468000
05
#469000
b11101011 ?
b1110 >
15
#470000
05
#471000
b11101100 ?
b1111 >
15
#472000
05
#473000
b11101101 ?
b10000 >
15
#474000
05
#475000
b11101110 ?
0)
b0 >
15
#476000
05
#477000
b11101111 ?
b1 >
15
#478000
05
#479000
b11110000 ?
b10 >
15
#480000
05
#481000
b11110001 ?
b11 >
15
#482000
05
#483000
b11110010 ?
b100 >
15
#484000
05
#485000
b11110011 ?
b101 >
15
#486000
05
#487000
b11110100 ?
b110 >
15
#488000
05
#489000
b11110101 ?
b111 >
15
#490000
05
#491000
b11110110 ?
b1000 >
15
#492000
05
#493000
b11110111 ?
b1001 >
15
#494000
05
#495000
b11111000 ?
b1010 >
15
#496000
05
#497000
b11111001 ?
b1011 >
15
#498000
05
#499000
b11111010 ?
b1100 >
15
#500000
05
#501000
b11111011 ?
b1101 >
15
#502000
05
#503000
b11111100 ?
b1110 >
15
#504000
05
#505000
b11111101 ?
b1111 >
15
#506000
05
#507000
b11111110 ?
b10000 >
15
#508000
05
#509000
b11111111 ?
1)
b0 >
15
#510000
05
#511000
b100000000 ?
b1 >
15
#512000
05
#513000
b100000001 ?
b10 >
15
#514000
05
#515000
b100000010 ?
b11 >
15
#516000
05
#517000
b100000011 ?
b100 >
15
#518000
05
#519000
b100000100 ?
b101 >
15
#520000
05
#521000
b100000101 ?
b110 >
15
#522000
05
#523000
b100000110 ?
b111 >
15
#524000
05
#525000
b100000111 ?
b1000 >
15
#526000
05
#527000
b100001000 ?
b1001 >
15
#528000
05
#529000
b100001001 ?
b1010 >
15
#530000
05
#531000
b100001010 ?
b1011 >
15
#532000
05
#533000
b100001011 ?
b1100 >
15
#534000
05
#535000
b100001100 ?
b1101 >
15
#536000
05
#537000
b100001101 ?
b1110 >
15
#538000
05
#539000
b100001110 ?
b1111 >
15
#540000
05
#541000
b100001111 ?
b10000 >
15
#542000
05
#543000
b1 `
0%
0#
1"
1$
b0 ?
0)
b0 >
15
#544000
05
#545000
b1 ?
b1 >
15
#546000
05
#547000
b10 ?
b10 >
15
#548000
05
#549000
b11 ?
b11 >
15
#550000
05
#551000
b100 ?
b100 >
15
#552000
05
#553000
b101 ?
b101 >
15
#554000
05
#555000
b110 ?
b110 >
15
#556000
05
#557000
b111 ?
b111 >
15
#558000
05
#559000
b1000 ?
b1000 >
15
#560000
05
#561000
b1001 ?
b1001 >
15
#562000
05
#563000
b1010 ?
b1010 >
15
#564000
05
#565000
b1011 ?
b1011 >
15
#566000
05
#567000
b1100 ?
b1100 >
15
#568000
05
#569000
b1101 ?
b1101 >
15
#570000
05
#571000
b1110 ?
b1110 >
15
#572000
05
#573000
b1111 ?
b1111 >
15
#574000
05
#575000
b10000 ?
b10000 >
15
#576000
05
#577000
1P
b10001 ?
1)
b0 >
15
#578000
05
#579000
b10010 ?
b1 >
15
#580000
05
#581000
b10011 ?
b10 >
15
#582000
05
#583000
b10100 ?
b11 >
15
#584000
05
#585000
b10101 ?
b100 >
15
#586000
05
#587000
b10110 ?
b101 >
15
#588000
05
#589000
b10111 ?
b110 >
15
#590000
05
#591000
b11000 ?
b111 >
15
#592000
05
#593000
b11001 ?
b1000 >
15
#594000
05
#595000
b11010 ?
b1001 >
15
#596000
05
#597000
b11011 ?
b1010 >
15
#598000
05
#599000
b11100 ?
b1011 >
15
#600000
05
#601000
b11101 ?
b1100 >
15
#602000
05
#603000
b11110 ?
b1101 >
15
#604000
05
#605000
b11111 ?
b1110 >
15
#606000
05
#607000
b100000 ?
b1111 >
15
#608000
05
#609000
b100001 ?
b10000 >
15
#610000
05
#611000
b100010 ?
0)
b0 >
15
#612000
05
#613000
b100011 ?
b1 >
15
#614000
05
#615000
b100100 ?
b10 >
15
#616000
05
#617000
b100101 ?
b11 >
15
#618000
05
#619000
b100110 ?
b100 >
15
#620000
05
#621000
b100111 ?
b101 >
15
#622000
05
#623000
b101000 ?
b110 >
15
#624000
05
#625000
b101001 ?
b111 >
15
#626000
05
#627000
b101010 ?
b1000 >
15
#628000
05
#629000
b101011 ?
b1001 >
15
#630000
05
#631000
b101100 ?
b1010 >
15
#632000
05
#633000
b101101 ?
b1011 >
15
#634000
05
#635000
b101110 ?
b1100 >
15
#636000
05
#637000
b101111 ?
b1101 >
15
#638000
05
#639000
b110000 ?
b1110 >
15
#640000
05
#641000
b110001 ?
b1111 >
15
#642000
05
#643000
b110010 ?
b10000 >
15
#644000
05
#645000
0B
1A
b110011 ?
1)
b0 >
15
#646000
05
#647000
b110100 ?
b1 >
15
#648000
05
#649000
b110101 ?
b10 >
15
#650000
05
#651000
b110110 ?
b11 >
15
#652000
05
#653000
b110111 ?
b100 >
15
#654000
05
#655000
b111000 ?
b101 >
15
#656000
05
#657000
b111001 ?
b110 >
15
#658000
05
#659000
b111010 ?
b111 >
15
#660000
05
#661000
b111011 ?
b1000 >
15
#662000
05
#663000
b111100 ?
b1001 >
15
#664000
05
#665000
b111101 ?
b1010 >
15
#666000
05
#667000
b111110 ?
b1011 >
15
#668000
05
#669000
b111111 ?
b1100 >
15
#670000
05
#671000
b1000000 ?
b1101 >
15
#672000
05
#673000
b1000001 ?
b1110 >
15
#674000
05
#675000
b1000010 ?
b1111 >
15
#676000
05
#677000
b1000011 ?
b10000 >
15
#678000
05
#679000
b1000100 ?
0)
b0 >
15
#680000
05
#681000
b1000101 ?
b1 >
15
#682000
05
#683000
b1000110 ?
b10 >
15
#684000
05
#685000
b1000111 ?
b11 >
15
#686000
05
#687000
b1001000 ?
b100 >
15
#688000
05
#689000
b1001001 ?
b101 >
15
#690000
05
#691000
b1001010 ?
b110 >
15
#692000
05
#693000
b1001011 ?
b111 >
15
#694000
05
#695000
b1001100 ?
b1000 >
15
#696000
05
#697000
b1001101 ?
b1001 >
15
#698000
05
#699000
b1001110 ?
b1010 >
15
#700000
05
#701000
b1001111 ?
b1011 >
15
#702000
05
#703000
b1010000 ?
b1100 >
15
#704000
05
#705000
b1010001 ?
b1101 >
15
#706000
05
#707000
b1010010 ?
b1110 >
15
#708000
05
#709000
b1010011 ?
b1111 >
15
#710000
05
#711000
b1010100 ?
b10000 >
15
#712000
05
#713000
b1010101 ?
1)
b0 >
15
#714000
05
#715000
b1010110 ?
b1 >
15
#716000
05
#717000
b1010111 ?
b10 >
15
#718000
05
#719000
b1011000 ?
b11 >
15
#720000
05
#721000
b1011001 ?
b100 >
15
#722000
05
#723000
b1011010 ?
b101 >
15
#724000
05
#725000
b1011011 ?
b110 >
15
#726000
05
#727000
b1011100 ?
b111 >
15
#728000
05
#729000
b1011101 ?
b1000 >
15
#730000
05
#731000
b1011110 ?
b1001 >
15
#732000
05
#733000
b1011111 ?
b1010 >
15
#734000
05
#735000
b1100000 ?
b1011 >
15
#736000
05
#737000
b1100001 ?
b1100 >
15
#738000
05
#739000
b1100010 ?
b1101 >
15
#740000
05
#741000
b1100011 ?
b1110 >
15
#742000
05
